MANIFEST.in
license.txt
pyproject.toml
readme.rst
setup.cfg
setup.py
OpenGL/__init__.py
OpenGL/_bytes.py
OpenGL/_configflags.py
OpenGL/_null.py
OpenGL/_opaque.py
OpenGL/acceleratesupport.py
OpenGL/constant.py
OpenGL/constants.py
OpenGL/contextdata.py
OpenGL/converters.py
OpenGL/error.py
OpenGL/extensions.py
OpenGL/images.py
OpenGL/latebind.py
OpenGL/lazywrapper.py
OpenGL/logs.py
OpenGL/plugins.py
OpenGL/version.py
OpenGL/wrapper.py
OpenGL/AGL/__init__.py
OpenGL/DLLS/GLE_WIN32_README.txt
OpenGL/DLLS/README.md
OpenGL/DLLS/freeglut32.vc10.dll
OpenGL/DLLS/freeglut32.vc14.dll
OpenGL/DLLS/freeglut32.vc9.dll
OpenGL/DLLS/freeglut64.vc10.dll
OpenGL/DLLS/freeglut64.vc14.dll
OpenGL/DLLS/freeglut64.vc9.dll
OpenGL/DLLS/freeglut_COPYING.txt
OpenGL/DLLS/freeglut_README.txt
OpenGL/DLLS/gle32.vc10.dll
OpenGL/DLLS/gle32.vc14.dll
OpenGL/DLLS/gle32.vc9.dll
OpenGL/DLLS/gle64.vc10.dll
OpenGL/DLLS/gle64.vc14.dll
OpenGL/DLLS/gle64.vc9.dll
OpenGL/DLLS/gle_AUTHORS
OpenGL/DLLS/gle_COPYING
OpenGL/DLLS/gle_COPYING.src
OpenGL/EGL/__init__.py
OpenGL/EGL/debug.py
OpenGL/EGL/gbmdevice.py
OpenGL/EGL/ANDROID/__init__.py
OpenGL/EGL/ANDROID/blob_cache.py
OpenGL/EGL/ANDROID/framebuffer_target.py
OpenGL/EGL/ANDROID/image_native_buffer.py
OpenGL/EGL/ANDROID/native_fence_sync.py
OpenGL/EGL/ANDROID/recordable.py
OpenGL/EGL/ANGLE/__init__.py
OpenGL/EGL/ANGLE/d3d_share_handle_client_buffer.py
OpenGL/EGL/ANGLE/device_d3d.py
OpenGL/EGL/ANGLE/query_surface_pointer.py
OpenGL/EGL/ANGLE/surface_d3d_texture_2d_share_handle.py
OpenGL/EGL/ANGLE/window_fixed_size.py
OpenGL/EGL/ARM/__init__.py
OpenGL/EGL/ARM/pixmap_multisample_discard.py
OpenGL/EGL/EXT/__init__.py
OpenGL/EGL/EXT/buffer_age.py
OpenGL/EGL/EXT/client_extensions.py
OpenGL/EGL/EXT/create_context_robustness.py
OpenGL/EGL/EXT/device_base.py
OpenGL/EGL/EXT/device_drm.py
OpenGL/EGL/EXT/device_enumeration.py
OpenGL/EGL/EXT/device_openwf.py
OpenGL/EGL/EXT/device_query.py
OpenGL/EGL/EXT/image_dma_buf_import.py
OpenGL/EGL/EXT/multiview_window.py
PyOpenGLAlwaysWorking.egg-info/PKG-INFO
PyOpenGLAlwaysWorking.egg-info/SOURCES.txt
PyOpenGLAlwaysWorking.egg-info/dependency_links.txt
PyOpenGLAlwaysWorking.egg-info/top_level.txt
