Metadata-Version: 2.1
Name: PyOpenGLAlwaysWorking
Version: 3.1.100
Summary: Standard OpenGL bindings for Python
Home-page: http://pyopengl.sourceforge.net
Download-URL: https://pypi.org/project/PyOpenGL/
Author: Mike C. Fletcher
Author-email: mcfletch@vrplumber.com
License: BSD
Keywords: Graphics,3D,OpenGL,GLU,GLUT,GLE,GLX,EXT,ARB,Mesa,ctypes
Classifier: License :: OSI Approved :: BSD License
Classifier: Programming Language :: Python
Classifier: Programming Language :: Python :: 2
Classifier: Programming Language :: Python :: 3
Classifier: Topic :: Multimedia :: Graphics :: 3D Rendering
Classifier: Topic :: Software Development :: Libraries :: Python Modules
Classifier: Intended Audience :: Developers
